Metadata-Version: 2.1
Name: django-query-builder
Version: 3.2.1
Summary: Build complex nested queries
Home-page: https://github.com/ambitioninc/django-query-builder
Author: Wes Okes
Author-email: wes.okes@gmail.com
License: MIT
Keywords: django,database,query,sql,postgres,upsert
Classifier: Programming Language :: Python
Classifier: Programming Language :: Python :: 3.8
Classifier: Programming Language :: Python :: 3.9
Classifier: Intended Audience :: Developers
Classifier: License :: OSI Approved :: MIT License
Classifier: Operating System :: OS Independent
Classifier: Framework :: Django
Classifier: Framework :: Django :: 2.2
Classifier: Framework :: Django :: 3.0
Classifier: Framework :: Django :: 3.1
Classifier: Framework :: Django :: 3.2
Classifier: Framework :: Django :: 4.0
Classifier: Framework :: Django :: 4.1
License-File: LICENSE
Requires-Dist: Django >=3.2
Requires-Dist: pytz >=2015.6
Requires-Dist: fleming >=0.6.0
